fileshare/__init__.py
fileshare/main.py
fileshare-1.0.1.dist-info/entry_points.txt
fileshare-1.0.1.dist-info/WHEEL
fileshare-1.0.1.dist-info/METADATA
fileshare-1.0.1.dist-info/RECORD
