Metadata-Version: 2.1
Name: fileshare
Version: 1.0.1
Summary: Small utility to easily upload to/download from Volafile.org
Author: aidan
Author-email: achaplin3@gatech.edu
Requires-Python: >=3.7,<4.0
Classifier: Programming Language :: Python :: 3
Classifier: Programming Language :: Python :: 3.7
Classifier: Programming Language :: Python :: 3.8
Classifier: Programming Language :: Python :: 3.9
Requires-Dist: requests (>=2.25.1,<3.0.0)
Requires-Dist: tqdm (>=4.61.0,<5.0.0)
Requires-Dist: volapi (>=5.22.0,<6.0.0)
